LICENSE.txt
MANIFEST.in
README.md
setup.py
examples/basic_usage/Basic_Usage.ipynb
examples/basic_usage/basic_usage.files
examples/basic_usage/basic_usage_R1.fastq
examples/basic_usage/basic_usage_R2.fastq
mothur_py/__init__.py
mothur_py/core.py
mothur_py/utils.py
mothur_py.egg-info/PKG-INFO
mothur_py.egg-info/SOURCES.txt
mothur_py.egg-info/dependency_links.txt
mothur_py.egg-info/top_level.txt
tests/test_data/test_fasta_1.fasta