Metadata-Version: 1.1
Name: mothur-py
Version: 0.4.0
Summary: Python wrapper for the bioinformatics tool mothur
Home-page: https://github.com/campenr/mothur-py
Author: Richard Campen
Author-email: richard@campen.co
License: Modified BSD License
Keywords: mothur bioinformatics
Platform: UNKNOWN
Classifier: Development Status :: 4 - Beta
Classifier: Intended Audience :: End Users/Desktop
Classifier: Intended Audience :: Science/Research
Classifier: License :: OSI Approved :: BSD License
Classifier: Natural Language :: English
Classifier: Operating System :: OS Independent
Classifier: Programming Language :: Python :: 3
Classifier: Topic :: Scientific/Engineering :: Bio-Informatics
